rfc3339_validator.py
rfc3339_validator-0.1.3.dist-info/AUTHORS.rst
rfc3339_validator-0.1.3.dist-info/LICENSE
rfc3339_validator-0.1.3.dist-info/METADATA
rfc3339_validator-0.1.3.dist-info/WHEEL
rfc3339_validator-0.1.3.dist-info/top_level.txt
rfc3339_validator-0.1.3.dist-info/RECORD
