Metadata-Version: 2.1
Name: rfc3339_validator
Version: 0.1.3
Summary: A pure python RFC3339 validator
Home-page: https://github.com/naimetti/rfc3339-validator
Author: Nicolas Aimetti
Author-email: naimetti@yahoo.com.ar
License: MIT license
Keywords: rfc3339 validator
Platform: UNKNOWN
Classifier: Development Status :: 2 - Pre-Alpha
Classifier: Intended Audience :: Developers
Classifier: License :: OSI Approved :: MIT License
Classifier: Natural Language :: English
Classifier: Programming Language :: Python :: 2
Classifier: Programming Language :: Python :: 2.7
Classifier: Programming Language :: Python :: 3
Classifier: Programming Language :: Python :: 3.5
Classifier: Programming Language :: Python :: 3.6
Classifier: Programming Language :: Python :: 3.7
Classifier: Programming Language :: Python :: 3.8
Requires-Python: >=2.7, !=3.0.*, !=3.1.*, !=3.2.*, !=3.3.*, !=3.4.*
